pytest_pyreport/__init__.py
pytest_pyreport/plugin.py
pytest_pyreport/templates/template.html
pytest_pyreport-1.6.0.dist-info/LICENSE
pytest_pyreport-1.6.0.dist-info/METADATA
pytest_pyreport-1.6.0.dist-info/WHEEL
pytest_pyreport-1.6.0.dist-info/entry_points.txt
pytest_pyreport-1.6.0.dist-info/top_level.txt
pytest_pyreport-1.6.0.dist-info/RECORD
