Metadata-Version: 2.1
Name: pytest-pyreport
Version: 1.6.0
Summary: PyReport is a lightweight reporting plugin for Pytest that provides concise HTML report
Home-page: https://github.com/ToghrulMirzayev/pytest-pyreport
Author: Toghrul Mirzayev
Author-email: togrul.mirzoev@gmail.com
License: MIT
Keywords: pytest_pyreport,python,pytest,report,slack,telegram,messenger,pyreport
Classifier: Framework :: Pytest
Classifier: Operating System :: OS Independent
Classifier: License :: OSI Approved :: MIT License
Classifier: Programming Language :: Python :: 3
Classifier: Topic :: Software Development :: Testing
Requires-Python: >=3.7
License-File: LICENSE
Requires-Dist: Jinja2
Requires-Dist: pytest
Requires-Dist: matplotlib
Requires-Dist: requests
Requires-Dist: logstyle
